[
  {
    "id": "1",
    "title": "1. 나와 내 가족이 사고 싶은 상품을 판매합니다.", 
    "imgUrl":"/images/About/about01.jpg",
    "content":  "컬리는 미각적,심미적으로 만족감을 주면서 사람의 몸에 이로운 상품이 우리의 삶까지 변화시킬 수 있다고 믿습니다. 내가 먹고 쓰는 것이 곧 '나'이니까요. 안정성, 맛, 상업성 등 여러 면에서 만족스로울 만한, 최상의 상품을 고르기 위해 직접 먹어보고 사용해 보며 여러 차례에 걸쳐 꼼꼼하게 검증합니다.",
    "view": "컬리의 품질 기준 더 알아보기 〉"
  },
  {
    "id": "2",
    "title": "2. 나와 내 가족이 사고 싶은 상품을 판매합니다.", 
    "imgUrl":"/images/About/about02.jpg",
    "content":  "컬리는 미각적,심미적으로 만족감을 주면서 사람의 몸에 이로운 상품이 우리의 삶까지 변화시킬 수 있다고 믿습니다. 내가 먹고 쓰는 것이 곧 '나'이니까요. 안정성, 맛, 상업성 등 여러 면에서 만족스로울 만한, 최상의 상품을 고르기 위해 직접 먹어보고 사용해 보며 여러 차례에 걸쳐 꼼꼼하게 검증합니다.",
    "view": "컬리의 품질 기준 더 알아보기 〉"
  },
  {
    "id": "3",
    "title": "3. 나와 내 가족이 사고 싶은 상품을 판매합니다.", 
    "imgUrl":"/images/About/about03.jpg",
    "content":  "컬리는 미각적,심미적으로 만족감을 주면서 사람의 몸에 이로운 상품이 우리의 삶까지 변화시킬 수 있다고 믿습니다. 내가 먹고 쓰는 것이 곧 '나'이니까요. 안정성, 맛, 상업성 등 여러 면에서 만족스로울 만한, 최상의 상품을 고르기 위해 직접 먹어보고 사용해 보며 여러 차례에 걸쳐 꼼꼼하게 검증합니다.",
    "view": "컬리의 품질 기준 더 알아보기 〉"
  },
  {
    "id": "4",
    "title": "4. 나와 내 가족이 사고 싶은 상품을 판매합니다.", 
    "imgUrl":"/images/About/about04.jpg",
    "content":  "컬리는 미각적,심미적으로 만족감을 주면서 사람의 몸에 이로운 상품이 우리의 삶까지 변화시킬 수 있다고 믿습니다. 내가 먹고 쓰는 것이 곧 '나'이니까요. 안정성, 맛, 상업성 등 여러 면에서 만족스로울 만한, 최상의 상품을 고르기 위해 직접 먹어보고 사용해 보며 여러 차례에 걸쳐 꼼꼼하게 검증합니다.",
    "view": "컬리의 품질 기준 더 알아보기 〉"
  },
  {
    "id": "5",
    "title": "5. 나와 내 가족이 사고 싶은 상품을 판매합니다.", 
    "imgUrl":"/images/About/about05.jpg",
    "content":  "컬리는 미각적,심미적으로 만족감을 주면서 사람의 몸에 이로운 상품이 우리의 삶까지 변화시킬 수 있다고 믿습니다. 내가 먹고 쓰는 것이 곧 '나'이니까요. 안정성, 맛, 상업성 등 여러 면에서 만족스로울 만한, 최상의 상품을 고르기 위해 직접 먹어보고 사용해 보며 여러 차례에 걸쳐 꼼꼼하게 검증합니다.",
    "view": "컬리의 품질 기준 더 알아보기 〉"
  },
  {
    "id": "6",
    "title": "6. 나와 내 가족이 사고 싶은 상품을 판매합니다.", 
    "imgUrl":"/images/About/about06.jpg",
    "content":  "컬리는 미각적,심미적으로 만족감을 주면서 사람의 몸에 이로운 상품이 우리의 삶까지 변화시킬 수 있다고 믿습니다. 내가 먹고 쓰는 것이 곧 '나'이니까요. 안정성, 맛, 상업성 등 여러 면에서 만족스로울 만한, 최상의 상품을 고르기 위해 직접 먹어보고 사용해 보며 여러 차례에 걸쳐 꼼꼼하게 검증합니다.",
    "view": "컬리의 품질 기준 더 알아보기 〉"
  }
]